README
findfiles.py
setup.py
findfiles.egg-info/PKG-INFO
findfiles.egg-info/SOURCES.txt
findfiles.egg-info/dependency_links.txt
findfiles.egg-info/top_level.txt