Metadata-Version: 1.0
Name: findfiles
Version: 0.0.4
Summary: simple iterator for finding files on disk
Home-page: https://github.com/rranshous/findfiles
Author: Robby Ranshous
Author-email: rranshous@gmail.com
License: UNKNOWN
Keywords: find
Platform: UNKNOWN
Classifier: Development Status :: 5 - Production/Stable
Classifier: Topic :: Utilities
Classifier: Programming Language :: Python :: 2.6
Classifier: Programming Language :: Python :: 2.7
